LICENSE
README.md
documentation/platform/ASSETS.md
documentation/platform/ORGANIZATION.md
documentation/platform/README.md
pixelbin/__init__.py
pixelbin/common/__init__.py
pixelbin/common/aiohttp_helper.py
pixelbin/common/constants.py
pixelbin/common/date_helper.py
pixelbin/common/exceptions.py
pixelbin/common/utils.py
pixelbin/platform/OAuthClient.py
pixelbin/platform/PixelbinClient.py
pixelbin/platform/PixelbinConfig.py
pixelbin/platform/PlatformAPIClient.py
pixelbin/platform/Predictions.py
pixelbin/platform/__init__.py
pixelbin/platform/enums.py
pixelbin/platform/models/AddCredentialsRequest.py
pixelbin/platform/models/AddCredentialsResponse.py
pixelbin/platform/models/AddPresetRequest.py
pixelbin/platform/models/AddPresetResponse.py
pixelbin/platform/models/AppOrgDetails.py
pixelbin/platform/models/AppSchema.py
pixelbin/platform/models/AssetsValidator.py
pixelbin/platform/models/BaseSchema.py
pixelbin/platform/models/CreateFolderRequest.py
pixelbin/platform/models/DeleteMultipleFilesRequest.py
pixelbin/platform/models/Delimiter.py
pixelbin/platform/models/ErrorSchema.py
pixelbin/platform/models/FileUploadRequest.py
pixelbin/platform/models/FilesResponse.py
pixelbin/platform/models/FoldersResponse.py
pixelbin/platform/models/GetAncestorsResponse.py
pixelbin/platform/models/GetPresetsResponse.py
pixelbin/platform/models/GetTransformationContextSuccessResponse.py
pixelbin/platform/models/ListFilesResponse.py
pixelbin/platform/models/OrganizationDetailSchema.py
pixelbin/platform/models/OrganizationValidator.py
pixelbin/platform/models/PresignedUrl.py
pixelbin/platform/models/PresignedUrlV2.py
pixelbin/platform/models/SignedUploadRequest.py
pixelbin/platform/models/SignedUploadRequestV2.py
pixelbin/platform/models/SignedUploadResponse.py
pixelbin/platform/models/SignedUploadV2Response.py
pixelbin/platform/models/TransformationModuleResponse.py
pixelbin/platform/models/TransformationModulesResponse.py
pixelbin/platform/models/TransformationValidator.py
pixelbin-4.3.0.dist-info/LICENSE
pixelbin-4.3.0.dist-info/METADATA
pixelbin-4.3.0.dist-info/WHEEL
pixelbin-4.3.0.dist-info/RECORD
