Metadata-Version: 2.1
Name: pixelbin
Version: 4.3.0
Summary: Pixelbin SDK for Python
Home-page: https://github.com/pixelbin-dev/pixelbin-python-sdk
License: MIT
Keywords: Pixelbin
Author: Pixelbin
Author-email: dev@pixelbin.io
Requires-Python: >=3.8,<4.0
Classifier: License :: OSI Approved :: MIT License
Classifier: Programming Language :: Python :: 3
Classifier: Programming Language :: Python :: 3.8
Classifier: Programming Language :: Python :: 3.9
Classifier: Programming Language :: Python :: 3.10
Classifier: Programming Language :: Python :: 3.11
Classifier: Programming Language :: Python :: 3.12
Requires-Dist: aiohttp (>=3.8.1,<4.0.0)
Requires-Dist: coverage (>=7.2.1,<8.0.0)
Requires-Dist: marshmallow (>=3.15.0,<4.0.0)
Requires-Dist: pytest (>=7.2.2,<8.0.0)
Requires-Dist: pytz (>=2022.1,<2023.0)
Requires-Dist: ujson (>=5.2.0,<6.0.0)
Project-URL: Repository, https://github.com/pixelbin-dev/pixelbin-python-sdk
